ficaria/__init__.py
ficaria/feature_selection.py
ficaria/missing_imputation.py
ficaria/utils.py
ficaria-0.1.0.dist-info/licenses/LICENSE
tests/test_feature_selection.py
tests/test_missing_imputation.py
tests/test_utils.py
ficaria-0.1.0.dist-info/METADATA
ficaria-0.1.0.dist-info/WHEEL
ficaria-0.1.0.dist-info/top_level.txt
ficaria-0.1.0.dist-info/RECORD
