Metadata-Version: 2.4
Name: ficaria
Version: 0.1.0
Summary: Feature selection and missing data imputation
Author-email: Aleksandra Kwiatkowska <aleksandra.kwiatkowska263@gmail.com>, Małgorzata Mokwa <malgosiam628@gmail.com>, Bogumiła Okrojek <bogumila.okrojek@gmail.com>
Project-URL: Homepage, https://github.com/team-ficaria/ficaria
Project-URL: Repository, https://github.com/team-ficaria/ficaria
Keywords: fuzzy,feature selection,missing data,imputation,machine learning,scikit-learn
Classifier: Development Status :: 5 - Production/Stable
Classifier: Intended Audience :: Developers
Classifier: Intended Audience :: Science/Research
Classifier: Programming Language :: Python :: 3
Classifier: Programming Language :: Python :: 3.11
Classifier: Topic :: Software Development :: Libraries
Classifier: Topic :: Scientific/Engineering :: Artificial Intelligence
Classifier: Topic :: Scientific/Engineering :: Information Analysis
Requires-Python: >=3.11
License-File: LICENSE
Requires-Dist: kneed>=0.8.5
Requires-Dist: numpy>=1.26.4
Requires-Dist: pandas>=2.1.4
Requires-Dist: scikit-learn>=1.4.0
Requires-Dist: scipy>=1.11.4
Requires-Dist: joblib>=1.5.3
Provides-Extra: dev
Requires-Dist: pytest>=7.4.0; extra == "dev"
Dynamic: license-file
